tradejini_api/__init__.py
tradejini_api/auth.py
tradejini_api/cli.py
tradejini_api/main.py
tradejini_api/nxtradstream.py
tradejini_api/openapi_client/__init__.py
tradejini_api/openapi_client/api_client.py
tradejini_api/openapi_client/api_response.py
tradejini_api/openapi_client/configuration.py
tradejini_api/openapi_client/exceptions.py
tradejini_api/openapi_client/py.typed
tradejini_api/openapi_client/rest.py
tradejini_api/openapi_client/__pycache__/__init__.cpython-313.pyc
tradejini_api/openapi_client/__pycache__/api_client.cpython-313.pyc
tradejini_api/openapi_client/__pycache__/api_response.cpython-313.pyc
tradejini_api/openapi_client/__pycache__/configuration.cpython-313.pyc
tradejini_api/openapi_client/__pycache__/exceptions.cpython-313.pyc
tradejini_api/openapi_client/__pycache__/rest.cpython-313.pyc
tradejini_api/openapi_client/api/__init__.py
tradejini_api/openapi_client/api/account_api.py
tradejini_api/openapi_client/api/advance_orders_api.py
tradejini_api/openapi_client/api/authorization_api.py
tradejini_api/openapi_client/api/chart_data_api.py
tradejini_api/openapi_client/api/funds_api.py
tradejini_api/openapi_client/api/orders_api.py
tradejini_api/openapi_client/api/symbol_details_api.py
tradejini_api/openapi_client/api/__pycache__/__init__.cpython-313.pyc
tradejini_api/openapi_client/api/__pycache__/account_api.cpython-313.pyc
tradejini_api/openapi_client/api/__pycache__/advance_orders_api.cpython-313.pyc
tradejini_api/openapi_client/api/__pycache__/authorization_api.cpython-313.pyc
tradejini_api/openapi_client/api/__pycache__/chart_data_api.cpython-313.pyc
tradejini_api/openapi_client/api/__pycache__/funds_api.cpython-313.pyc
tradejini_api/openapi_client/api/__pycache__/orders_api.cpython-313.pyc
tradejini_api/openapi_client/api/__pycache__/symbol_details_api.cpython-313.pyc
tradejini_api/openapi_client/models/__init__.py
tradejini_api/openapi_client/models/access_token.py
tradejini_api/openapi_client/models/ask_data_list.py
tradejini_api-1.0.0.dist-info/METADATA
tradejini_api-1.0.0.dist-info/WHEEL
tradejini_api-1.0.0.dist-info/entry_points.txt
tradejini_api-1.0.0.dist-info/top_level.txt
tradejini_api-1.0.0.dist-info/RECORD
