Metadata-Version: 2.4
Name: tradejini_api
Version: 1.0.0
Summary: Professional Python SDK & Automation Suite for Tradejini CubePlus
Requires-Python: >=3.9
Requires-Dist: pydantic>=2.0
Requires-Dist: requests
Requires-Dist: urllib3
Requires-Dist: python-dotenv
Requires-Dist: pyotp
Requires-Dist: websocket-client
Requires-Dist: click
Requires-Dist: pandas
